mtecconnect3dcp/Dosingpump.py
mtecconnect3dcp/Duomix.py
mtecconnect3dcp/DuomixPlus.py
mtecconnect3dcp/Mixingpump.py
mtecconnect3dcp/MixingpumpPlus.py
mtecconnect3dcp/ModbusMachine.py
mtecconnect3dcp/OPCUAMachine.py
mtecconnect3dcp/Printhead.py
mtecconnect3dcp/Pump.py
mtecconnect3dcp/Smp.py
mtecconnect3dcp/SmpPlus.py
mtecconnect3dcp/__init__.py
mtecconnect3dcp-2.1.0.dist-info/METADATA
mtecconnect3dcp-2.1.0.dist-info/WHEEL
mtecconnect3dcp-2.1.0.dist-info/top_level.txt
mtecconnect3dcp-2.1.0.dist-info/RECORD
