Metadata-Version: 2.4
Name: mtecconnect3dcp
Version: 2.1.0
Summary: OPC-UA client classes for m-tec machines (Mixingpump, Printhead, Dosingpump)
Home-page: https://github.com/m-tec-com/mtecConnect3DCP
Author: Paul Richter
Author-email: paul.richter@m-tec.com
Project-URL: Source, https://github.com/m-tec-com/mtecConnect3DCP
Project-URL: Tracker, https://github.com/m-tec-com/mtecConnect3DCP/issues
Keywords: opcua m-tec connect 3dcp automation m2m mixingpump pump printhead dosingpump duo-mix flow-matic smp p20 p50 3d concrete printing
Classifier: Programming Language :: Python :: 3
Classifier: License :: OSI Approved :: MIT License
Classifier: Operating System :: OS Independent
Requires-Python: >=3.7
Requires-Dist: asyncua>=1.0.0
Requires-Dist: pyserial>=3.5
Dynamic: author
Dynamic: author-email
Dynamic: classifier
Dynamic: description
Dynamic: description-content-type
Dynamic: home-page
Dynamic: keywords
Dynamic: project-url
Dynamic: requires-dist
Dynamic: requires-python
Dynamic: summary
